{
  "condition_id": "0x01a0ad20748ad1e1123be94867fca9743939b9b19f370b262d12efb967746ac0",
  "question": "Bitcoin Up or Down - January 11, 3:00PM-3:15PM ET",
  "up": [
    {
      "t": 1768160651,
      "p": 0.52
    },
    {
      "t": 1768160711,
      "p": 0.525
    },
    {
      "t": 1768160772,
      "p": 0.525
    },
    {
      "t": 1768160831,
      "p": 0.525
    },
    {
      "t": 1768160891,
      "p": 0.535
    },
    {
      "t": 1768160951,
      "p": 0.535
    },
    {
      "t": 1768161012,
      "p": 0.535
    },
    {
      "t": 1768161072,
      "p": 0.535
    },
    {
      "t": 1768161131,
      "p": 0.535
    },
    {
      "t": 1768161191,
      "p": 0.535
    },
    {
      "t": 1768161251,
      "p": 0.535
    },
    {
      "t": 1768161311,
      "p": 0.535
    },
    {
      "t": 1768161381,
      "p": 0.545
    },
    {
      "t": 1768161431,
      "p": 0.545
    },
    {
      "t": 1768161491,
      "p": 0.555
    },
    {
      "t": 1768161551,
      "p": 0.555
    },
    {
      "t": 1768161616,
      "p": 0.575
    }
  ],
  "down": [
    {
      "t": 1768160654,
      "p": 0.48
    },
    {
      "t": 1768160715,
      "p": 0.475
    },
    {
      "t": 1768160775,
      "p": 0.475
    },
    {
      "t": 1768160834,
      "p": 0.475
    },
    {
      "t": 1768160894,
      "p": 0.465
    },
    {
      "t": 1768160954,
      "p": 0.465
    },
    {
      "t": 1768161017,
      "p": 0.465
    },
    {
      "t": 1768161076,
      "p": 0.465
    },
    {
      "t": 1768161134,
      "p": 0.465
    },
    {
      "t": 1768161193,
      "p": 0.465
    },
    {
      "t": 1768161254,
      "p": 0.465
    },
    {
      "t": 1768161315,
      "p": 0.465
    },
    {
      "t": 1768161396,
      "p": 0.455
    },
    {
      "t": 1768161434,
      "p": 0.455
    },
    {
      "t": 1768161494,
      "p": 0.445
    },
    {
      "t": 1768161554,
      "p": 0.445
    },
    {
      "t": 1768161625,
      "p": 0.425
    }
  ]
}