{
  "condition_id": "0x8b9343e273ccdf42899b664c2321e2cf7dca17e78e23986aaab48ce77f001832",
  "question": "Bitcoin Up or Down - January 12, 1:00AM-1:15AM ET",
  "up": [
    {
      "t": 1768196651,
      "p": 0.495
    },
    {
      "t": 1768196711,
      "p": 0.495
    },
    {
      "t": 1768196770,
      "p": 0.495
    },
    {
      "t": 1768196830,
      "p": 0.495
    },
    {
      "t": 1768196891,
      "p": 0.495
    },
    {
      "t": 1768196950,
      "p": 0.505
    },
    {
      "t": 1768197011,
      "p": 0.505
    },
    {
      "t": 1768197071,
      "p": 0.505
    },
    {
      "t": 1768197130,
      "p": 0.515
    },
    {
      "t": 1768197190,
      "p": 0.515
    },
    {
      "t": 1768197250,
      "p": 0.515
    },
    {
      "t": 1768197311,
      "p": 0.515
    },
    {
      "t": 1768197370,
      "p": 0.515
    },
    {
      "t": 1768197430,
      "p": 0.505
    },
    {
      "t": 1768197490,
      "p": 0.505
    },
    {
      "t": 1768197550,
      "p": 0.505
    },
    {
      "t": 1768197614,
      "p": 0.505
    }
  ],
  "down": [
    {
      "t": 1768196654,
      "p": 0.505
    },
    {
      "t": 1768196715,
      "p": 0.505
    },
    {
      "t": 1768196773,
      "p": 0.505
    },
    {
      "t": 1768196833,
      "p": 0.505
    },
    {
      "t": 1768196894,
      "p": 0.505
    },
    {
      "t": 1768196953,
      "p": 0.495
    },
    {
      "t": 1768197015,
      "p": 0.495
    },
    {
      "t": 1768197074,
      "p": 0.495
    },
    {
      "t": 1768197133,
      "p": 0.485
    },
    {
      "t": 1768197194,
      "p": 0.485
    },
    {
      "t": 1768197253,
      "p": 0.485
    },
    {
      "t": 1768197315,
      "p": 0.485
    },
    {
      "t": 1768197373,
      "p": 0.485
    },
    {
      "t": 1768197434,
      "p": 0.495
    },
    {
      "t": 1768197494,
      "p": 0.495
    },
    {
      "t": 1768197553,
      "p": 0.495
    },
    {
      "t": 1768197622,
      "p": 0.495
    }
  ]
}